CHANGES.rst
CONTRIBUTORS.rst
LICENSE
MANIFEST.in
Makefile
README.rst
setup.py
salvo/__init__.py
salvo/output.py
salvo/pgbar.py
salvo/run.py
salvo/scenario.py
salvo/util.py
salvo.egg-info/PKG-INFO
salvo.egg-info/SOURCES.txt
salvo.egg-info/dependency_links.txt
salvo.egg-info/entry_points.txt
salvo.egg-info/not-zip-safe
salvo.egg-info/requires.txt
salvo.egg-info/top_level.txt
salvo/tests/__init__.py
salvo/tests/support.py
salvo/tests/test_output.py
salvo/tests/test_run.py
salvo/tests/test_util.py