Metadata-Version: 1.1
Name: salvo
Version: 0.2
Summary: Simple HTTP Load tester
Home-page: https://github.com/tarekziade/salvo
Author: Tarek Ziade
Author-email: tarek@ziade.org
License: UNKNOWN
Platform: UNKNOWN
Classifier: License :: OSI Approved :: Apache Software License
Classifier: Programming Language :: Python
Classifier: Programming Language :: Python :: 3.6
Classifier: Programming Language :: Python :: 3.7
Classifier: Programming Language :: Python :: 3.8
Classifier: Programming Language :: Python :: 3.9
